utls/__init__.py
utls/open_n_load_mag_qsm_2files.py
utls/show_mri_3d.py
nifti_load_crop-0.0.1.dist-info/METADATA
nifti_load_crop-0.0.1.dist-info/WHEEL
nifti_load_crop-0.0.1.dist-info/top_level.txt
nifti_load_crop-0.0.1.dist-info/RECORD
